pysilk/__init__.py
pysilk/_silk.abi3.so
pysilk/build.py
pysilk_cffi-0.1.0rc1.dist-info/METADATA
pysilk_cffi-0.1.0rc1.dist-info/WHEEL
pysilk_cffi-0.1.0rc1.dist-info/top_level.txt
pysilk_cffi-0.1.0rc1.dist-info/RECORD
