Metadata-Version: 2.1
Name: pysilk-cffi
Version: 0.1.0rc1
Summary: silk encode and decode
Home-page: https://github.com/synodriver/pysilk-cffi
Author: synodriver
Author-email: diguohuangjiajinweijun@gmail.com
License: GPLv3
Keywords: silk,encode,decode,pcm,audio
Platform: UNKNOWN
Classifier: Development Status :: 4 - Beta
Classifier: Operating System :: OS Independent
Classifier: License :: OSI Approved :: BSD License
Classifier: Topic :: Multimedia :: Sound/Audio
Classifier: Programming Language :: C
Classifier: Programming Language :: Python
Classifier: Programming Language :: Python :: 3.6
Classifier: Programming Language :: Python :: 3.7
Classifier: Programming Language :: Python :: 3.8
Classifier: Programming Language :: Python :: 3.9
Classifier: Programming Language :: Python :: 3.10
Classifier: Programming Language :: Python :: Implementation :: CPython
Classifier: Programming Language :: Python :: Implementation :: PyPy
Requires-Python: >=3.6
Requires-Dist: cffi (>=1.0.0)
